mcp_agent_x-0.0.2.dist-info/licenses/LICENSE
mcpx/__init__.py
mcpx/agent.py
mcpx/cli.py
mcpx/config.py
mcpx/main.py
mcpx/repl.py
mcpx/utils.py
mcpx/defaults/config.json
mcpx/defaults/system_prompt.md
mcp_agent_x-0.0.2.dist-info/METADATA
mcp_agent_x-0.0.2.dist-info/WHEEL
mcp_agent_x-0.0.2.dist-info/entry_points.txt
mcp_agent_x-0.0.2.dist-info/top_level.txt
mcp_agent_x-0.0.2.dist-info/RECORD
