Metadata-Version: 2.4
Name: mcp-agent-x
Version: 0.0.2
Summary: Minimal MCP Agent REPL interface
License: MIT License
Requires-Python: >=3.11
License-File: LICENSE
Requires-Dist: asyncio>=3.4.3
Requires-Dist: langchain-google-genai>=2.1.2
Requires-Dist: langchain-openai>=0.1.20
Requires-Dist: mcp-use>=1.1.5
Requires-Dist: python-dotenv>=1.1.0
Requires-Dist: rich>=13.5.0
Requires-Dist: prompt_toolkit>=3.0.38
Requires-Dist: platformdirs>=4.2.0
Requires-Dist: click>=8.1.7
Provides-Extra: dev
Requires-Dist: pre-commit>=4.2.0; extra == "dev"
Requires-Dist: pytest>=7.4.0; extra == "dev"
Requires-Dist: pytest-asyncio>=0.23.0; extra == "dev"
Requires-Dist: ruff>=0.2.0; extra == "dev"
Dynamic: license-file
